mcp_paperless_ngx/__init__.py
mcp_paperless_ngx/env.py
mcp_paperless_ngx/paperless_api.py
mcp_paperless_ngx/server.py
mcp_paperless_ngx-0.1.3.dist-info/METADATA
mcp_paperless_ngx-0.1.3.dist-info/WHEEL
mcp_paperless_ngx-0.1.3.dist-info/entry_points.txt
mcp_paperless_ngx-0.1.3.dist-info/RECORD
