Metadata-Version: 2.4
Name: mcp-paperless-ngx
Version: 0.1.3
Summary: A MCP server for Paperless-ngx
Author-email: Simon Erhardt <simon@erhardt.consulting>
Requires-Python: >=3.12
Requires-Dist: mcp>=1.7.1
Requires-Dist: pypaperless>=4.0.0
